[
  {
    "model": "products.product",
    "pk": 1,
    "fields": {
      "product_type": "BIKES",
      "product_group": "URBAN",
      "frame": "FABIKE C3",
      "name": "SINGLE SPEED",
      "title": "Thought for maximum simplicity.",
      "fork": "FABIKE C3",
      "wheels": "FABIKE aluminium disc",
      "tyres": "Challenge Paris-Roubaix clincher",
      "max_tyre_size": null,
      "crankset": "Shimano Alfine Gates CDX",
      "shift_levers": "Shimano Alfine",
      "derailleurs": "N/A",
      "casette_or_sprocket": "Gates CDX",
      "chain_or_belt": "Gates CDX",
      "brakes": "Shimano SLX + 105 calipers",
      "handlebar": "FABIKE aluminium flat bar",
      "stem": "FABIKE aluminium stem",
      "saddle": "Fabric Scoop Cromo",
      "seatpost": "FABIKE aluminium seatpost",
      "seat_clamp": null,
      "headset": null,
      "seatpost_diameter": null,
      "bottom_bracket": null,
      "dropouts": null,
      "is_bike": true,
      "weight": null,
      "weight_alloy": "7.5",
      "weight_carbon": "7.2",
      "price": null,
      "price_alloy": "2999",
      "price_carbon": "3490",
      "price_comment": "The components in carbon fibre will be: wheels, handlebar, seatpost, saddle rail.",
      "image01": "c3_ss_lr.jpg",
      "img_url01": null,
      "image02": "c3_ss_hr_background.jpg",
      "img_url02": null
    }
  },
  {
    "model": "products.product",
    "pk": 2,
    "fields": {
      "product_type": "BIKES",
      "product_group": "URBAN",
      "frame": "FABIKE C3",
      "name": "ALFINE",
      "title": "Thought for maximum versatility.",
      "fork": "FABIKE C3",
      "wheels": "FABIKE aluminium disc with Alfine 11 speed",
      "tyres": "Challenge Paris-Roubaix clincher",
      "max_tyre_size": null,
      "crankset": "Shimano Alfine Gates CDX",
      "shift_levers": "Shimano Alfine",
      "derailleurs": "N/A",
      "casette_or_sprocket": "Gates CDX",
      "chain_or_belt": "Gates CDX",
      "brakes": "Shimano SLX + 105 calipers",
      "handlebar": "FABIKE aluminium flat bar",
      "stem": "FABIKE aluminium stem",
      "saddle": "Fabric Scoop Cromo",
      "seatpost": "FABIKE aluminium seatpost",
      "seat_clamp": null,
      "headset": null,
      "seatpost_diameter": null,
      "bottom_bracket": null,
      "dropouts": null,
      "is_bike": true,
      "weight": null,
      "weight_alloy": "9.2",
      "weight_carbon": "8.9",
      "price": null,
      "price_alloy": "3390",
      "price_carbon": "3890",
      "price_comment": "The components in carbon fibre will be: wheels, handlebar, seatpost, saddle rail.",
      "image01": "c3_alfine_lr.jpg",
      "img_url01": null,
      "image02": "c3_alfine_hr_background.jpg",
      "img_url02": null
    }
  },
  {
    "model": "products.product",
    "pk": 3,
    "fields": {
      "product_type": "BIKES",
      "product_group": "URBAN",
      "frame": "FABIKE C3",
      "name": "ROHLOFF",
      "title": "Versatility, reliability and design ride together.",
      "fork": "FABIKE C3",
      "wheels": "FABIKE aluminium disc with Rohloff SpeedHub",
      "tyres": "Challenge Strada Bianca 33mm",
      "max_tyre_size": null,
      "crankset": "Shimano Alfine with Gates CDX",
      "shift_levers": "Rohloff",
      "derailleurs": "N/A",
      "casette_or_sprocket": "Gates CDX",
      "chain_or_belt": "Gates CDX",
      "brakes": "Shimano XT",
      "handlebar": "FABIKE aluminium flat bar",
      "stem": "FABIKE aluminium stem",
      "saddle": "Fabric Scoop Cromo",
      "seatpost": "FABIKE aluminium seatpost",
      "seat_clamp": null,
      "headset": null,
      "seatpost_diameter": null,
      "bottom_bracket": null,
      "dropouts": null,
      "is_bike": true,
      "weight": null,
      "weight_alloy": "9.2",
      "weight_carbon": "8.9",
      "price": null,
      "price_alloy": "3990",
      "price_carbon": "4490",
      "price_comment": "The components in carbon fibre will be: wheels, handlebar, seatpost, saddle rail.",
      "image01": "c3_rohloff_lr.jpg",
      "img_url01": null,
      "image02": "c3_rohloff_hr_background.jpg",
      "img_url02": null
    }
  },
  {
    "model": "products.product",
    "pk": 4,
    "fields": {
      "product_type": "BIKES",
      "product_group": "URBAN",
      "frame": "FABIKE T2",
      "name": "ROHLOFF",
      "title": "Versatility, reliability and durability ride together.",
      "fork": "FABIKE RG",
      "wheels": "FABIKE aluminium disc with Rohloff SpeedHub",
      "tyres": "Challenge Strada Bianca 33mm",
      "max_tyre_size": null,
      "crankset": "Shimano Zee with Gates CDX",
      "shift_levers": "Rohloff",
      "derailleurs": "N/A",
      "casette_or_sprocket": "Gates CDX",
      "chain_or_belt": "Gates CDX",
      "brakes": "Shimano XT",
      "handlebar": "FABIKE aluminium flat bar",
      "stem": "FABIKE aluminium stem",
      "saddle": "Fabric Scoop Cromo",
      "seatpost": "FABIKE aluminium seatpost",
      "seat_clamp": null,
      "headset": null,
      "seatpost_diameter": null,
      "bottom_bracket": null,
      "dropouts": null,
      "is_bike": true,
      "weight": null,
      "weight_alloy": "9.8",
      "weight_carbon": "9.5",
      "price": null,
      "price_alloy": "4490",
      "price_carbon": "4890",
      "price_comment": "The components in carbon fibre will be: wheels, handlebar, seatpost, saddle rail.",
      "image01": "t2x_rohloff_lr.jpg",
      "img_url01": null,
      "image02": "t2x_rohloff_hr_background.jpg",
      "img_url02": null
    }
  },
  {
    "model": "products.product",
    "pk": 5,
    "fields": {
      "product_type": "BIKES",
      "product_group": "ALL ROAD",
      "frame": "FABIKE C3",
      "name": "ROHLOFF DROP BAR",
      "title": "Versatility, reliability and design ride together.",
      "fork": "FABIKE C3",
      "wheels": "FABIKE aluminium disc with Rohloff SpeedHub",
      "tyres": "Challenge Strada Bianca 33mm",
      "max_tyre_size": null,
      "crankset": "Shimano Zee with Gates CDX",
      "shift_levers": "SRAM Force + Rohbox",
      "derailleurs": "N/A",
      "casette_or_sprocket": "Gates CDX",
      "chain_or_belt": "Gates CDX",
      "brakes": "SRAM Force",
      "handlebar": "FABIKE aluminium flat bar",
      "stem": "FABIKE aluminium stem",
      "saddle": "Fabric Scoop Cromo",
      "seatpost": "FABIKE aluminium seatpost",
      "seat_clamp": null,
      "headset": null,
      "seatpost_diameter": null,
      "bottom_bracket": null,
      "dropouts": null,
      "is_bike": true,
      "weight": null,
      "weight_alloy": "9.4",
      "weight_carbon": "9.1",
      "price": null,
      "price_alloy": "4390",
      "price_carbon": "4890",
      "price_comment": "The components in carbon fibre will be: wheels, handlebar, seatpost, saddle rail.",
      "image01": "c3_rohloff_drop_lr.jpg",
      "img_url01": null,
      "image02": "c3_rohloff_drop_hr_background.jpg",
      "img_url02": null
    }
  },
  {
    "model": "products.product",
    "pk": 6,
    "fields": {
      "product_type": "BIKES",
      "product_group": "ALL ROAD",
      "frame": "FABIKE T2",
      "name": "ROHLOFF DROP BAR",
      "title": "Versatility, reliability and durability ride together.",
      "fork": "FABIKE RG",
      "wheels": "FABIKE aluminium disc with Rohloff SpeedHub",
      "tyres": "Challenge Gravel Grinder 38mm",
      "max_tyre_size": null,
      "crankset": "Shimano Zee with Gates CDX",
      "shift_levers": "SRAM Force + Rohbox",
      "derailleurs": "N/A",
      "casette_or_sprocket": "Gates CDX",
      "chain_or_belt": "Gates CDX",
      "brakes": "SRAM Force",
      "handlebar": "FABIKE aluminium drop bar",
      "stem": "FABIKE aluminium stem",
      "saddle": "Fabric Scoop Cromo",
      "seatpost": "FABIKE aluminium seatpost",
      "seat_clamp": null,
      "headset": null,
      "seatpost_diameter": null,
      "bottom_bracket": null,
      "dropouts": null,
      "is_bike": true,
      "weight": null,
      "weight_alloy": "9.9",
      "weight_carbon": "9.6",
      "price": null,
      "price_alloy": "4890",
      "price_carbon": "5390",
      "price_comment": "The components in carbon fibre will be: wheels, handlebar, seatpost, saddle rail.",
      "image01": "t2x_rohloff_drop_lr.jpg",
      "img_url01": null,
      "image02": "t2x_rohloff_drop_hr_background.jpg",
      "img_url02": null
    }
  },
  {
    "model": "products.product",
    "pk": 7,
    "fields": {
      "product_type": "BIKES",
      "product_group": "ALL ROAD",
      "frame": "FABIKE T2",
      "name": "FORCE",
      "title": "The essence of a great adventure.",
      "fork": "FABIKE RG",
      "wheels": "FABIKE aluminium disc",
      "tyres": "Challenge Gravel Grinder 38mm",
      "max_tyre_size": null,
      "crankset": "SRAM Force 1",
      "shift_levers": "SRAM Force 1",
      "derailleurs": "N/A",
      "casette_or_sprocket": "SRAM XG 1175",
      "chain_or_belt": "SRAM PC 1170",
      "brakes": "SRAM Force",
      "handlebar": "FABIKE aluminium drop bar",
      "stem": "FABIKE aluminium stem",
      "saddle": "Fabric Scoop Cromo",
      "seatpost": "FABIKE aluminium seatpost",
      "seat_clamp": null,
      "headset": null,
      "seatpost_diameter": null,
      "bottom_bracket": null,
      "dropouts": null,
      "is_bike": true,
      "weight": null,
      "weight_alloy": "8.0",
      "weight_carbon": "7.7",
      "price": null,
      "price_alloy": "3890",
      "price_carbon": "4390",
      "price_comment": "The components in carbon fibre will be: wheels, handlebar, seatpost, saddle rail.",
      "image01": "t2x_force_cx1_lr.jpg",
      "img_url01": null,
      "image02": "t2x_force_cx1_hr_background.jpg",
      "img_url02": null
    }
  },
  {
    "model": "products.product",
    "pk": 8,
    "fields": {
      "product_type": "BIKES",
      "product_group": "ALL ROAD",
      "frame": "FABIKE T2",
      "name": "FORCE AXS",
      "title": "The next level of a great adventure.",
      "fork": "FABIKE RG",
      "wheels": "FABIKE aluminium disc",
      "tyres": "Challenge Gravel Grinder 38mm",
      "max_tyre_size": "SRAM Force 1 AXS",
      "crankset": "SRAM Force 1 AXS",
      "shift_levers": "SRAM Force AXS",
      "derailleurs": "N/A",
      "casette_or_sprocket": "SRAM XG 1295",
      "chain_or_belt": "SRAM Force 12s",
      "brakes": "SRAM Force AXS",
      "handlebar": "FABIKE aluminium drop bar",
      "stem": "FABIKE aluminium stem",
      "saddle": "Fabric Scoop Cromo",
      "seatpost": "FABIKE aluminium seatpost",
      "seat_clamp": null,
      "headset": null,
      "seatpost_diameter": null,
      "bottom_bracket": null,
      "dropouts": null,
      "is_bike": true,
      "weight": null,
      "weight_alloy": "8.0",
      "weight_carbon": "7.7",
      "price": null,
      "price_alloy": "4590",
      "price_carbon": "5090",
      "price_comment": "The components in carbon fibre will be: wheels, handlebar, seatpost, saddle rail.",
      "image01": "t2x_force_axs_lr.jpg",
      "img_url01": null,
      "image02": "t2x_force_axs_hr_background.jpg",
      "img_url02": null
    }
  },
  {
    "model": "products.product",
    "pk": 9,
    "fields": {
      "product_type": "BIKES",
      "product_group": "ALL ROAD",
      "frame": "FABIKE T2",
      "name": "GRX",
      "title": "The confidence for a great adventure.",
      "fork": "FABIKE RG",
      "wheels": "FABIKE aluminium disc",
      "tyres": "Challenge Gravel Grinder 38mm",
      "max_tyre_size": null,
      "crankset": "Shimano RX-810-1",
      "shift_levers": "Shimano RX-810-1",
      "derailleurs": "N/A",
      "casette_or_sprocket": "Shimano HG-800",
      "chain_or_belt": "Shimano HG-701",
      "brakes": "Shimano RX-801",
      "handlebar": "FABIKE aluminium drop bar",
      "stem": "FABIKE aluminium stem",
      "saddle": "Fabric Scoop Cromo",
      "seatpost": "FABIKE aluminium seatpost",
      "seat_clamp": null,
      "headset": null,
      "seatpost_diameter": null,
      "bottom_bracket": null,
      "dropouts": null,
      "is_bike": true,
      "weight": null,
      "weight_alloy": "8.2",
      "weight_carbon": "7.9",
      "price": null,
      "price_alloy": "3390",
      "price_carbon": "3890",
      "price_comment": "The components in carbon fibre will be: wheels, handlebar, seatpost, saddle rail.",
      "image01": "t2x_grx_lr.jpg",
      "img_url01": null,
      "image02": "t2x_grx_hr_background.jpg",
      "img_url02": null
    }
  },
  {
    "model": "products.product",
    "pk": 10,
    "fields": {
      "product_type": "BIKES",
      "product_group": "ROAD",
      "frame": "FABIKE C3",
      "name": "ULTEGRA",
      "title": "Speed and design at your service.",
      "fork": "FABIKE C3",
      "wheels": "FABIKE aluminium disc",
      "tyres": "Challenge Strada 25mm",
      "max_tyre_size": null,
      "crankset": "Shimano Ultegra R8000",
      "shift_levers": "Shimano Ultegra R8020",
      "derailleurs": "Shimano Ultegra R8000",
      "casette_or_sprocket": "Shimano Ultegra R8000",
      "chain_or_belt": "Shimano Ultegra R8000",
      "brakes": "Shimano Ultegra R8020",
      "handlebar": "FABIKE aluminium drop bar",
      "stem": "FABIKE aluminium stem",
      "saddle": "Fabric Scoop Cromo",
      "seatpost": "FABIKE aluminium seatpost",
      "seat_clamp": null,
      "headset": null,
      "seatpost_diameter": null,
      "bottom_bracket": null,
      "dropouts": null,
      "is_bike": true,
      "weight": null,
      "weight_alloy": "7.6",
      "weight_carbon": "7.3",
      "price": null,
      "price_alloy": "3390",
      "price_carbon": "3890",
      "price_comment": "The components in carbon fibre will be: wheels, handlebar, seatpost, saddle rail.",
      "image01": "c3_ultegra_hr.jpg",
      "img_url01": null,
      "image02": "c3_ultegra_hr_background.jpg",
      "img_url02": null
    }
  },
  {
    "model": "products.product",
    "pk": 11,
    "fields": {
      "product_type": "BIKES",
      "product_group": "ROAD",
      "frame": "FABIKE C3",
      "name": "ULTEGRA Di2",
      "title": "Technology and design at your service.",
      "fork": "FABIKE C3",
      "wheels": "FABIKE aluminium disc",
      "tyres": "Challenge Strada 25mm",
      "max_tyre_size": null,
      "crankset": "Shimano Ultegra R8000",
      "shift_levers": "Shimano Ultegra R8070",
      "derailleurs": "Shimano Ultegra R8050",
      "casette_or_sprocket": "Shimano Ultegra R8000",
      "chain_or_belt": "Shimano Ultegra R8000",
      "brakes": "Shimano Ultegra R8020",
      "handlebar": "FABIKE aluminium drop bar",
      "stem": "FABIKE aluminium stem",
      "saddle": "Fabric Scoop Cromo",
      "seatpost": "FABIKE aluminium seatpost",
      "seat_clamp": null,
      "headset": null,
      "seatpost_diameter": null,
      "bottom_bracket": null,
      "dropouts": null,
      "is_bike": true,
      "weight": null,
      "weight_alloy": "7.6",
      "weight_carbon": "7.3",
      "price": null,
      "price_alloy": "3990",
      "price_carbon": "4490",
      "price_comment": "The components in carbon fibre will be: wheels, handlebar, seatpost, saddle rail.",
      "image01": "c3_ultegra_di2_hr.jpg",
      "img_url01": null,
      "image02": "c3_ultegra_di2_hr_background.jpg",
      "img_url02": null
    }
  },
  {
    "model": "products.product",
    "pk": 12,
    "fields": {
      "product_type": "BIKES",
      "product_group": "ROAD",
      "frame": "FABIKE C3",
      "name": "FORCE AXS",
      "title": "The next level of speed.",
      "fork": "FABIKE C3",
      "wheels": "FABIKE aluminium disc",
      "tyres": "Challenge Strada 25mm",
      "max_tyre_size": null,
      "crankset": "SRAM Force 1 AXS",
      "shift_levers": "SRAM Force AXS",
      "derailleurs": "SRAM Force AXS",
      "casette_or_sprocket": "SRAM XG 1270",
      "chain_or_belt": "SRAM Force 12s",
      "brakes": "SRAM Force AXS",
      "handlebar": "FABIKE aluminium drop bar",
      "stem": "FABIKE aluminium stem",
      "saddle": "Fabric Scoop Cromo",
      "seatpost": "FABIKE aluminium seatpost",
      "seat_clamp": null,
      "headset": null,
      "seatpost_diameter": null,
      "bottom_bracket": null,
      "dropouts": null,
      "is_bike": true,
      "weight": null,
      "weight_alloy": "7.6",
      "weight_carbon": "7.3",
      "price": null,
      "price_alloy": "3990",
      "price_carbon": "4490",
      "price_comment": "The components in carbon fibre will be: wheels, handlebar, seatpost, saddle rail.",
      "image01": "c3_force_axs_hr.jpg",
      "img_url01": null,
      "image02": "c3_force_axs_hr_background.jpg",
      "img_url02": null
    }
  },
  {
    "model": "products.product",
    "pk": 13,
    "fields": {
      "product_type": "FRAMES",
      "product_group": "CARBON",
      "frame": "FABIKE C3",
      "name": "FRAME SET",
      "title": "The starting point to your unique bike experience.",
      "fork": "FABIKE C3 - Toray T800",
      "wheels": null,
      "tyres": null,
      "max_tyre_size": "32-33mm",
      "crankset": null,
      "shift_levers": null,
      "derailleurs": null,
      "casette_or_sprocket": null,
      "chain_or_belt": null,
      "brakes": "Disc brake Flat Mount",
      "handlebar": null,
      "stem": null,
      "saddle": null,
      "seatpost": null,
      "seat_clamp": "FABIKE anodized alloy",
      "headset": "FABIKE anodized alloy 1-1/8” 1-1/2”",
      "seatpost_diameter": "31.6mm",
      "bottom_bracket": "Press Fit 30, 68mm",
      "dropouts": "Front: thru axle 100x12mm; Rear: thru axle 142x12mm",
      "is_bike": false,
      "weight": "1.7",
      "weight_alloy": null,
      "weight_carbon": null,
      "price": "2390",
      "price_alloy": null,
      "price_carbon": null,
      "price_comment": "Includes Frame, Fork, headset, seat clamp",
      "image01": "c3frame_white.jpg",
      "img_url01": null,
      "image02": "c3frame_black.jpg",
      "img_url02": null
    }
  },
  {
    "model": "products.product",
    "pk": 14,
    "fields": {
      "product_type": "FRAMES",
      "product_group": "TITANIUM",
      "frame": "FABIKE T2",
      "name": "FRAME SET",
      "title": "The starting point to your unique bike experience.",
      "fork": "FABIKE RG - Toray T700",
      "wheels": null,
      "tyres": null,
      "max_tyre_size": "40-42mm x 700c*;  45-47mm x 650b*",
      "crankset": null,
      "shift_levers": null,
      "derailleurs": null,
      "casette_or_sprocket": null,
      "chain_or_belt": null,
      "brakes": "Disc brake Flat Mount",
      "handlebar": null,
      "stem": null,
      "saddle": null,
      "seatpost": null,
      "seat_clamp": "FABIKE anodized alloy",
      "headset": "FABIKE anodized alloy 1-1/8” 1-1/2”",
      "seatpost_diameter": "31.6mm",
      "bottom_bracket": "At your choice",
      "dropouts": "Front: thru axle 100x12mm; Rear: At your choice",
      "is_bike": false,
      "weight": "2.2",
      "weight_alloy": null,
      "weight_carbon": null,
      "price": "2790",
      "price_alloy": null,
      "price_carbon": null,
      "price_comment": "Includes Frame, Fork, headset, seat clamp",
      "image01": "t1frame_white.jpg",
      "img_url01": null,
      "image02": "t1frame_black.jpg",
      "img_url02": null
    }
  }
]